LICENSE_D-FSL_1_0_en.txt
README.txt
setup.py
Products/__init__.py
Products.CompoundField.egg-info/PKG-INFO
Products.CompoundField.egg-info/SOURCES.txt
Products.CompoundField.egg-info/dependency_links.txt
Products.CompoundField.egg-info/entry_points.txt
Products.CompoundField.egg-info/namespace_packages.txt
Products.CompoundField.egg-info/not-zip-safe
Products.CompoundField.egg-info/requires.txt
Products.CompoundField.egg-info/top_level.txt
Products/CompoundField/ArrayField.py
Products/CompoundField/ArrayWidget.py
Products/CompoundField/ClassGen.py
Products/CompoundField/CompoundField.py
Products/CompoundField/CompoundWidget.py
Products/CompoundField/EnhancedArrayWidget.py
Products/CompoundField/IArrayField.py
Products/CompoundField/ICompoundField.py
Products/CompoundField/__init__.py
Products/CompoundField/cfns.py
Products/CompoundField/config.py
Products/CompoundField/configure.zcml
Products/CompoundField/profiles.zcml
Products/CompoundField/setuphandlers.py
Products/CompoundField/utils.py
Products/CompoundField/validators.py
Products/CompoundField/version.txt
Products/CompoundField/doc/__init__.py
Products/CompoundField/doc/testATSchemaConsistency.txt
Products/CompoundField/doc/testArrayField.txt
Products/CompoundField/doc/testNestedArrayFields.txt
Products/CompoundField/doc/testXMLMarshall.txt
Products/CompoundField/i18n/generated.pot
Products/CompoundField/profiles/default/CompoundField_marker.txt
Products/CompoundField/profiles/default/cssregistry.xml
Products/CompoundField/profiles/default/factorytool.xml
Products/CompoundField/profiles/default/import_steps.xml
Products/CompoundField/profiles/default/jsregistry.xml
Products/CompoundField/profiles/default/metadata.xml
Products/CompoundField/profiles/default/skins.xml
Products/CompoundField/profiles/default/types.xml
Products/CompoundField/profiles/default/types/ArrayFieldTest.xml
Products/CompoundField/profiles/default/types/CompoundFieldTest.xml
Products/CompoundField/profiles/default/types/NestedArrayFieldTest.xml
Products/CompoundField/skins/CompoundField/ArrayFieldTest.gif
Products/CompoundField/skins/CompoundField/ArrayWidget.pt
Products/CompoundField/skins/CompoundField/CompoundFieldTest.gif
Products/CompoundField/skins/CompoundField/CompoundWidget.pt
Products/CompoundField/skins/CompoundField/EnhancedArrayWidget.pt
