Metadata-Version: 1.0
Name: Products.CompoundField
Version: 1.1
Summary: Compound- and Array-Field and -Widget for Archetypes
Home-page: http://plone.org/products/compoundfield
Author: BlueDynamics Alliance
Author-email: dev@bluedynamics.com
License: D-FSL (German Free Software Licence)
Keywords: web zope plone archetypes field widget
Platform: UNKNOWN
Classifier: Framework :: Plone
Classifier: Framework :: Zope2
Classifier: Programming Language :: Python
Classifier: Topic :: Software Development :: Libraries :: Python Modules
